{
  "index": {
    "title": "首页",
    "type": "page",
    "theme": {
      "layout": "raw"
    }
  },
  "download": {
    "title": "下载",
    "type": "page",
    "theme": {
      "layout": "raw"
    }
  },
  "document": {
    "title": "文档",
    "type": "menu",
    "items": {
      "tutorials": {
        "title": "教程",
        "type": "page"
      },
      "template": {
        "title": "提示模版",
        "type": "page",
        "theme": {
          "layout": "raw"
        }
      }
    }
  },
  "blog": {
    "title": "博客",
    "type": "page"
  }
}
